[{"pk": 1, "model": "fireblog.entry", "fields": {"body": "What", "title": "Test", "markup": "<p>What</p>", "author": 1, "intro": "I can't beleive I'm testing!", "published": "p", "date": "2012-08-30", "slug": "test"}}, {"pk": 2, "model": "fireblog.entry", "fields": {"body": "laksjdlaksdal\r\n\r\nHello!", "title": "LAKSjdalksd", "markup": "<p>laksjdlaksdal</p>\n<p>Hello!</p>", "author": 1, "intro": "ASLKDjal", "published": "p", "date": "2012-08-30", "slug": "laksjdalksd"}}, {"pk": 3, "model": "fireblog.entry", "fields": {"body": "ljaslkdjalsdjlafsa", "title": "dlkvdaljsflkamcsklaml", "markup": "<p>ljaslkdjalsdjlafsa</p>", "author": 1, "intro": "kljaslkajdlaskmd", "published": "p", "date": "2012-06-29", "slug": "dlkvdaljsflkamcsklaml"}}, {"pk": 4, "model": "fireblog.entry", "fields": {"body": "I have to have at least 11 posts to trigger pagination.", "title": "Hello", "markup": "<p>I have to have at least 11 posts to trigger pagination.</p>", "author": 1, "intro": "I just gotta push through to 11!", "published": "p", "date": "2012-09-15", "slug": "hello"}}, {"pk": 5, "model": "fireblog.entry", "fields": {"body": "lkajlsdkjasldjlaskdjalkma", "title": "ASKLdjasldj", "markup": "<p>lkajlsdkjasldjlaskdjalkma</p>", "author": 1, "intro": "klasjldajslkdal", "published": "p", "date": "2012-09-15", "slug": "askldjasldj"}}, {"pk": 6, "model": "fireblog.entry", "fields": {"body": "lkajslkdmaglanlamckamclllllllllllllllllllllla", "title": "aslkdajdl", "markup": "<p>lkajslkdmaglanlamckamclllllllllllllllllllllla</p>", "author": 1, "intro": "lkjalsdjalksfmalskmnalkfgal", "published": "p", "date": "2012-09-15", "slug": "aslkdajdl"}}, {"pk": 7, "model": "fireblog.entry", "fields": {"body": "klasjldkamsdklasdmlaksdmakldmaslkdmal", "title": "asklgjsdlkfnsljvslfnalkl", "markup": "<p>klasjldkamsdklasdmlaksdmakldmaslkdmal</p>", "author": 1, "intro": "jlkajsdlajdlakjsdlakmclkamflkasncalk", "published": "p", "date": "2012-09-15", "slug": "asklgjsdlkfnsljvslfnalkl"}}, {"pk": 8, "model": "fireblog.entry", "fields": {"body": "lkasdjalksdmaklsdmakldslaksdmalk", "title": "asldkaflam", "markup": "<p>lkasdjalksdmaklsdmakldslaksdmalk</p>", "author": 1, "intro": "lkaskdjalksdml", "published": "p", "date": "2012-09-15", "slug": "asldkaflam"}}, {"pk": 9, "model": "fireblog.entry", "fields": {"body": "kasdlaksdalsdkasldalsdka", "title": "alksdasldjalkda", "markup": "<p>kasdlaksdalsdkasldalsdka</p>", "author": 1, "intro": "laskldalksdmlaksdmalsdakl", "published": "p", "date": "2012-09-15", "slug": "alksdasldjalkda"}}, {"pk": 10, "model": "fireblog.entry", "fields": {"body": "lasldjalskjdalskdjalsdja", "title": "lkadjlasdjaalkd", "markup": "<p>lasldjalskjdalskdjalsdja</p>", "author": 1, "intro": "lkajsldalksdal", "published": "p", "date": "2012-09-15", "slug": "lkadjlasdjaalkd"}}, {"pk": 11, "model": "fireblog.entry", "fields": {"body": "lkasjldalsf", "title": "asdalsfkajsflj", "markup": "<p>lkasjldalsf</p>", "author": 1, "intro": "ljaklsdjalsjdlk", "published": "p", "date": "2012-09-15", "slug": "asdalsfkajsflj"}}]